{
	"graph_elements": [
		{ "data": { "id": "A"}, "position": { "x": 201, "y": 60 } },
		{ "data": { "id": "B"}, "position": { "x": 148, "y": 87 } },
		{ "data": { "id": "C"}, "position": { "x": 139, "y": 57 } },
		{ "data": { "id": "D"}, "position": { "x": 213, "y": 162 } },
		{ "data": { "id": "E"}, "position": { "x": 107, "y": 110 } },
		{ "data": { "id": "F"}, "position": { "x": 187, "y": 119 } },
		{ "data": { "id": "G"}, "position": { "x": 235, "y": 56 } },
		{ "data": { "id": "H"}, "position": { "x": 104, "y": 163 } },
		{ "data": { "id": "I"}, "position": { "x": 157, "y": 180 } },
		{ "data": { "id": "J"}, "position": { "x": 228, "y": 110 } },
		{ "data": { "id": "K"}, "position": { "x": 135, "y": 113 } },
		{ "data": { "id": "L"}, "position": { "x": 178, "y": 20 } },
		{ "data": { "id": "M"}, "position": { "x": 79, "y": 96 } },
		{ "data": { "id": "N"}, "position": { "x": 178, "y": 91 } },
		{ "data": { "id": "O"}, "position": { "x": 253, "y": 112 } },
		{ "data": { "id": "P"}, "position": { "x": 163, "y": 150 } },
		{ "data": { "id": "AB", "source": "A", "target": "B" } },
		{ "data": { "id": "AC", "source": "A", "target": "C" } },
		{ "data": { "id": "AF", "source": "A", "target": "F" } },
		{ "data": { "id": "AJ", "source": "A", "target": "J" } },
		{ "data": { "id": "AL", "source": "A", "target": "L" } },
		{ "data": { "id": "AO", "source": "A", "target": "O" } },
		{ "data": { "id": "BF", "source": "B", "target": "F" } },
		{ "data": { "id": "BM", "source": "B", "target": "M" } },
		{ "data": { "id": "BN", "source": "B", "target": "N" } },
		{ "data": { "id": "CE", "source": "C", "target": "E" } },
		{ "data": { "id": "CK", "source": "C", "target": "K" } },
		{ "data": { "id": "CL", "source": "C", "target": "L" } },
		{ "data": { "id": "DF", "source": "D", "target": "F" } },
		{ "data": { "id": "DI", "source": "D", "target": "I" } },
		{ "data": { "id": "DJ", "source": "D", "target": "J" } },
		{ "data": { "id": "DO", "source": "D", "target": "O" } },
		{ "data": { "id": "DP", "source": "D", "target": "P" } },
		{ "data": { "id": "EH", "source": "E", "target": "H" } },
		{ "data": { "id": "EP", "source": "E", "target": "P" } },
		{ "data": { "id": "FJ", "source": "F", "target": "J" } },
		{ "data": { "id": "FK", "source": "F", "target": "K" } },
		{ "data": { "id": "FP", "source": "F", "target": "P" } },
		{ "data": { "id": "GJ", "source": "G", "target": "J" } },
		{ "data": { "id": "GN", "source": "G", "target": "N" } },
		{ "data": { "id": "HI", "source": "H", "target": "I" } },
		{ "data": { "id": "HM", "source": "H", "target": "M" } },
		{ "data": { "id": "HP", "source": "H", "target": "P" } },
		{ "data": { "id": "IK", "source": "I", "target": "K" } },
		{ "data": { "id": "JO", "source": "J", "target": "O" } },
		{ "data": { "id": "KN", "source": "K", "target": "N" } },
		{ "data": { "id": "LN", "source": "L", "target": "N" } },
		{ "data": { "id": "NP", "source": "N", "target": "P" } }
	],
	"target": 7
}