{
	"graph_elements": [
		{ "data": { "id": "A"}, "position": { "x": 210, "y": 123 } },
		{ "data": { "id": "B"}, "position": { "x": 233, "y": 22 } },
		{ "data": { "id": "C"}, "position": { "x": 150, "y": 98 } },
		{ "data": { "id": "D"}, "position": { "x": 222, "y": 74 } },
		{ "data": { "id": "E"}, "position": { "x": 184, "y": 146 } },
		{ "data": { "id": "F"}, "position": { "x": 95, "y": 44 } },
		{ "data": { "id": "G"}, "position": { "x": 222, "y": 179 } },
		{ "data": { "id": "H"}, "position": { "x": 151, "y": 21 } },
		{ "data": { "id": "I"}, "position": { "x": 151, "y": 130 } },
		{ "data": { "id": "J"}, "position": { "x": 201, "y": 44 } },
		{ "data": { "id": "K"}, "position": { "x": 101, "y": 117 } },
		{ "data": { "id": "L"}, "position": { "x": 253, "y": 75 } },
		{ "data": { "id": "M"}, "position": { "x": 189, "y": 91 } },
		{ "data": { "id": "N"}, "position": { "x": 121, "y": 70 } },
		{ "data": { "id": "O"}, "position": { "x": 150, "y": 64 } },
		{ "data": { "id": "P"}, "position": { "x": 104, "y": 153 } },
		{ "data": { "id": "Q"}, "position": { "x": 76, "y": 94 } },
		{ "data": { "id": "AC", "source": "A", "target": "C" } },
		{ "data": { "id": "AD", "source": "A", "target": "D" } },
		{ "data": { "id": "AE", "source": "A", "target": "E" } },
		{ "data": { "id": "AG", "source": "A", "target": "G" } },
		{ "data": { "id": "AI", "source": "A", "target": "I" } },
		{ "data": { "id": "AL", "source": "A", "target": "L" } },
		{ "data": { "id": "BD", "source": "B", "target": "D" } },
		{ "data": { "id": "BM", "source": "B", "target": "M" } },
		{ "data": { "id": "CJ", "source": "C", "target": "J" } },
		{ "data": { "id": "CK", "source": "C", "target": "K" } },
		{ "data": { "id": "CM", "source": "C", "target": "M" } },
		{ "data": { "id": "CP", "source": "C", "target": "P" } },
		{ "data": { "id": "CQ", "source": "C", "target": "Q" } },
		{ "data": { "id": "DL", "source": "D", "target": "L" } },
		{ "data": { "id": "DM", "source": "D", "target": "M" } },
		{ "data": { "id": "DO", "source": "D", "target": "O" } },
		{ "data": { "id": "EG", "source": "E", "target": "G" } },
		{ "data": { "id": "EM", "source": "E", "target": "M" } },
		{ "data": { "id": "EO", "source": "E", "target": "O" } },
		{ "data": { "id": "FK", "source": "F", "target": "K" } },
		{ "data": { "id": "FO", "source": "F", "target": "O" } },
		{ "data": { "id": "FQ", "source": "F", "target": "Q" } },
		{ "data": { "id": "HJ", "source": "H", "target": "J" } },
		{ "data": { "id": "HM", "source": "H", "target": "M" } },
		{ "data": { "id": "HN", "source": "H", "target": "N" } },
		{ "data": { "id": "HO", "source": "H", "target": "O" } },
		{ "data": { "id": "IK", "source": "I", "target": "K" } },
		{ "data": { "id": "IM", "source": "I", "target": "M" } },
		{ "data": { "id": "IN", "source": "I", "target": "N" } },
		{ "data": { "id": "JL", "source": "J", "target": "L" } },
		{ "data": { "id": "JO", "source": "J", "target": "O" } },
		{ "data": { "id": "KN", "source": "K", "target": "N" } },
		{ "data": { "id": "KO", "source": "K", "target": "O" } },
		{ "data": { "id": "KP", "source": "K", "target": "P" } },
		{ "data": { "id": "KQ", "source": "K", "target": "Q" } },
		{ "data": { "id": "MO", "source": "M", "target": "O" } }
	],
	"target": 7
}