{
	"graph_elements": [
		{ "data": { "id": "A"}, "position": { "x": 145, "y": 80 } },
		{ "data": { "id": "B"}, "position": { "x": 118, "y": 66 } },
		{ "data": { "id": "C"}, "position": { "x": 113, "y": 119 } },
		{ "data": { "id": "D"}, "position": { "x": 157, "y": 181 } },
		{ "data": { "id": "E"}, "position": { "x": 163, "y": 52 } },
		{ "data": { "id": "F"}, "position": { "x": 147, "y": 29 } },
		{ "data": { "id": "G"}, "position": { "x": 116, "y": 165 } },
		{ "data": { "id": "H"}, "position": { "x": 117, "y": 37 } },
		{ "data": { "id": "I"}, "position": { "x": 151, "y": 134 } },
		{ "data": { "id": "J"}, "position": { "x": 157, "y": 111 } },
		{ "data": { "id": "K"}, "position": { "x": 191, "y": 19 } },
		{ "data": { "id": "L"}, "position": { "x": 188, "y": 111 } },
		{ "data": { "id": "M"}, "position": { "x": 191, "y": 69 } },
		{ "data": { "id": "N"}, "position": { "x": 216, "y": 46 } },
		{ "data": { "id": "AC", "source": "A", "target": "C" } },
		{ "data": { "id": "AF", "source": "A", "target": "F" } },
		{ "data": { "id": "AH", "source": "A", "target": "H" } },
		{ "data": { "id": "AI", "source": "A", "target": "I" } },
		{ "data": { "id": "AL", "source": "A", "target": "L" } },
		{ "data": { "id": "AM", "source": "A", "target": "M" } },
		{ "data": { "id": "BE", "source": "B", "target": "E" } },
		{ "data": { "id": "BF", "source": "B", "target": "F" } },
		{ "data": { "id": "BH", "source": "B", "target": "H" } },
		{ "data": { "id": "BJ", "source": "B", "target": "J" } },
		{ "data": { "id": "CG", "source": "C", "target": "G" } },
		{ "data": { "id": "CJ", "source": "C", "target": "J" } },
		{ "data": { "id": "DG", "source": "D", "target": "G" } },
		{ "data": { "id": "DI", "source": "D", "target": "I" } },
		{ "data": { "id": "EF", "source": "E", "target": "F" } },
		{ "data": { "id": "EH", "source": "E", "target": "H" } },
		{ "data": { "id": "EJ", "source": "E", "target": "J" } },
		{ "data": { "id": "EN", "source": "E", "target": "N" } },
		{ "data": { "id": "FH", "source": "F", "target": "H" } },
		{ "data": { "id": "FK", "source": "F", "target": "K" } },
		{ "data": { "id": "GI", "source": "G", "target": "I" } },
		{ "data": { "id": "IL", "source": "I", "target": "L" } },
		{ "data": { "id": "JL", "source": "J", "target": "L" } },
		{ "data": { "id": "JM", "source": "J", "target": "M" } },
		{ "data": { "id": "KM", "source": "K", "target": "M" } },
		{ "data": { "id": "LM", "source": "L", "target": "M" } },
		{ "data": { "id": "MN", "source": "M", "target": "N" } }
	],
	"target": 6
}